pytubelib/__init__.py
pytubelib-0.0.1.dist-info/LICENSE
pytubelib-0.0.1.dist-info/METADATA
pytubelib-0.0.1.dist-info/WHEEL
pytubelib-0.0.1.dist-info/top_level.txt
pytubelib-0.0.1.dist-info/RECORD
