Metadata-Version: 2.1
Name: pytubelib
Version: 0.0.1
Summary: PyTubeLib is a tool for interacting with the YouTube Data v3 API using Python. With PyTubeLib, you can search for channels and videos using keywords, get details about specific channels and videos, and search for the latest videos from a channel. The class is designed to handle common API errors and returns results in JSON format for easy processing.
Home-page: https://github.com/xXBlackDev9010Xx/PyTubeLib
Author: xXBlackDev9010Xx
Author-email: tecnoblue9010@gmail.com
Classifier: Programming Language :: Python :: 3
Classifier: License :: OSI Approved :: MIT License
Classifier: Operating System :: OS Independent
Requires-Python: >=3.8
License-File: LICENSE
Requires-Dist: google-api-python-client
Requires-Dist: google-auth-oauthlib
Requires-Dist: google-auth-httplib2
Requires-Dist: colors-terminal
